odoo9_addon_stock_scanner_receipt-9.0.1.0.0-py2.7-nspkg.pth
odoo_addons/stock_scanner_receipt/__openerp__.py
odoo_addons/stock_scanner_receipt/__init__.py
odoo_addons/stock_scanner_receipt/README.rst
odoo_addons/stock_scanner_receipt/data/Stock.scenario
odoo_addons/stock_scanner_receipt/data/Receipt/scanner_scenario_step_receipt_done.py
odoo_addons/stock_scanner_receipt/data/Receipt/scanner_scenario_step_receipt_unknown_location.py
odoo_addons/stock_scanner_receipt/data/Receipt/Receipt.scenario
odoo_addons/stock_scanner_receipt/data/Receipt/scanner_scenario_step_receipt_location_selection.py
odoo_addons/stock_scanner_receipt/data/Receipt/scanner_scenario_step_receipt_invalid_quantity.py
odoo_addons/stock_scanner_receipt/data/Receipt/scanner_scenario_step_receipt_quantity_selection.py
odoo_addons/stock_scanner_receipt/data/Receipt/scanner_scenario_step_receipt_unknown_picking.py
odoo_addons/stock_scanner_receipt/data/Receipt/scanner_scenario_step_receipt_invalid_prodlot.py
odoo_addons/stock_scanner_receipt/data/Receipt/scanner_scenario_step_receipt_prodlot_selection.py
odoo_addons/stock_scanner_receipt/data/Receipt/scanner_scenario_step_receipt_end_confirmation.py
odoo_addons/stock_scanner_receipt/data/Receipt/scanner_scenario_step_receipt_product_selection.py
odoo_addons/stock_scanner_receipt/data/Receipt/scanner_scenario_step_receipt_picking_selection.py
odoo_addons/stock_scanner_receipt/images/scenario.png
odoo9_addon_stock_scanner_receipt-9.0.1.0.0.dist-info/top_level.txt
odoo9_addon_stock_scanner_receipt-9.0.1.0.0.dist-info/WHEEL
odoo9_addon_stock_scanner_receipt-9.0.1.0.0.dist-info/RECORD
odoo9_addon_stock_scanner_receipt-9.0.1.0.0.dist-info/metadata.json
odoo9_addon_stock_scanner_receipt-9.0.1.0.0.dist-info/DESCRIPTION.rst
odoo9_addon_stock_scanner_receipt-9.0.1.0.0.dist-info/METADATA
odoo9_addon_stock_scanner_receipt-9.0.1.0.0.dist-info/namespace_packages.txt
